rich_ascii/NameAliases.txt
rich_ascii/__init__.py
rich_ascii/__main__.py
rich_ascii-0.2.0.dist-info/entry_points.txt
rich_ascii-0.2.0.dist-info/WHEEL
rich_ascii-0.2.0.dist-info/METADATA
rich_ascii-0.2.0.dist-info/RECORD
