Metadata-Version: 2.1
Name: rich-ascii
Version: 0.2.0
Summary: CLI tool to display the ASCII character code point information as a table.
License: Apache-2.0
Author: Simon Kennedy
Author-email: sffjunkie+code@gmail.com
Requires-Python: >=3.10,<4.0
Classifier: License :: OSI Approved :: Apache Software License
Classifier: Programming Language :: Python :: 3
Classifier: Programming Language :: Python :: 3.10
Requires-Dist: click (>=8.1.3,<9.0.0)
Requires-Dist: rich (>=12.5.1,<13.0.0)
